Metadata-Version: 1.1
Name: PyAndroid
Version: 1.1.3
Summary: Android information in python code
Home-page: https://pyandroid.000webhostapp.com/
Author: olokelo
Author-email: olokelo@gmail.com
License: MIT
Keywords: PyAndroid,AndroPy,olokelo,olokel0,python_android,android
Platform: UNKNOWN
Classifier: Development Status :: 3 - Alpha
Classifier: Intended Audience :: Science/Research
Classifier: Topic :: Scientific/Engineering :: Bio-Informatics
Classifier: License :: OSI Approved :: MIT License
Classifier: Programming Language :: Python :: 3
Classifier: Programming Language :: Python :: 3.1
Classifier: Programming Language :: Python :: 3.2
Classifier: Programming Language :: Python :: 3.3
Classifier: Programming Language :: Python :: 3.4
Classifier: Programming Language :: Python :: 3.5
Classifier: Programming Language :: Python :: 3.6
